imov/__init__.py
imov/main.py
imov-0.1.4.dist-info/METADATA
imov-0.1.4.dist-info/WHEEL
imov-0.1.4.dist-info/entry_points.txt
imov-0.1.4.dist-info/top_level.txt
imov-0.1.4.dist-info/RECORD
