Metadata-Version: 2.1
Name: imov
Version: 0.1.4
Summary: A Python Crawler for IMDB-TOP-250.
Home-page: https://github.com/doctoroyy/IMDB-TOP-250
Author: doctoroyy
Author-email: doctor.oyy@gmail.com
License: UNKNOWN
Platform: UNKNOWN
Requires-Dist: requests
Requires-Dist: openpyxl
Requires-Dist: lxml
Requires-Dist: setuptools
